tests/__init__.py
tests/conftest.py
tests/test_api_client.py
tests/test_integration.py
x8/__init__.py
x8/api_client.py
x8/config.py
x8/exceptions.py
x8/models.py
x8_client-0.1.8.dist-info/LICENSE
x8_client-0.1.8.dist-info/METADATA
x8_client-0.1.8.dist-info/WHEEL
x8_client-0.1.8.dist-info/top_level.txt
x8_client-0.1.8.dist-info/RECORD
